morningstreams/__init__.py
morningstreams/cli.py
morningstreams/core/__init__.py
morningstreams/core/client.py
morningstreams/core/engine.py
morningstreams/core/server.py
morningstreams/utils.py
morningstreams-0.2.3.dist-info/LICENSE
morningstreams-0.2.3.dist-info/METADATA
morningstreams-0.2.3.dist-info/WHEEL
morningstreams-0.2.3.dist-info/entry_points.txt
morningstreams-0.2.3.dist-info/RECORD
